{
  "ticker": "SDIG",
  "company_name": "Stronghold Digital Mining",
  "period": "2024_Q3",
  "period_type": "quarterly",
  "period_end_date": "2024-09-30",
  "currency": "USD",
  "unit": "millions",
  "source": "SEC 10-Q",
  "collected_date": "2026-02-26",
  "notes": "2024_Q3 revenue.",
  "income_statement": {
    "revenue": 8.02,
    "cogs": 11.51,
    "gross_profit": -3.48,
    "sga": 8.33,
    "depreciation": 8.62,
    "operating_income": -17.58,
    "net_income": -19.49,
    "ebit": -17.58,
    "eps_diluted": -1.34
  },
  "balance_sheet": {
    "total_assets": null,
    "current_assets": null,
    "cash_and_equivalents": null,
    "receivables": null,
    "ppe_net": null,
    "total_liabilities": null,
    "current_liabilities": null,
    "long_term_debt": null,
    "retained_earnings": null,
    "total_equity": null,
    "shares_outstanding_m": 151
  },
  "cash_flow_statement": {
    "operating_cash_flow": null,
    "investing_cash_flow": null,
    "financing_cash_flow": null,
    "capex": null,
    "free_cash_flow": 2.37
  },
  "market_data": {
    "stock_price": null,
    "market_cap": null,
    "btc_held": null
  }
}