{"MARA": {"ticker": "MARA", "price": 12.17, "prev_close": null, "currency": "USD", "exchange": "NCM", "market_cap": null}, "RIOT": {"ticker": "RIOT", "price": 19.185, "prev_close": null, "currency": "USD", "exchange": "NCM", "market_cap": null}, "CLSK": {"ticker": "CLSK", "price": 12.785, "prev_close": null, "currency": "USD", "exchange": "NCM", "market_cap": null}, "CORZ": {"ticker": "CORZ", "price": 20.745, "prev_close": null, "currency": "USD", "exchange": "NMS", "market_cap": null}, "HUT": {"ticker": "HUT", "price": 77.98, "prev_close": null, "currency": "USD", "exchange": "NMS", "market_cap": null}, "WULF": {"ticker": "WULF", "price": 22.355, "prev_close": null, "currency": "USD", "exchange": "NCM", "market_cap": null}, "IREN": {"ticker": "IREN", "price": 46.81, "prev_close": null, "currency": "USD", "exchange": "NMS", "market_cap": null}, "CIFR": {"ticker": "CIFR", "price": 18.17, "prev_close": null, "currency": "USD", "exchange": "NMS", "market_cap": null}, "BITF": {"ticker": "BITF", "price": 1.98, "prev_close": null, "currency": "USD", "exchange": "NGM", "market_cap": null}, "BTBT": {"ticker": "BTBT", "price": 1.56, "prev_close": null, "currency": "USD", "exchange": "NCM", "market_cap": null}, "BTDR": {"ticker": "BTDR", "price": 11.91, "prev_close": null, "currency": "USD", "exchange": "NCM", "market_cap": null}, "APLD": {"ticker": "APLD", "price": 34.42, "prev_close": null, "currency": "USD", "exchange": "NMS", "market_cap": null}, "FUFU": {"ticker": "FUFU", "price": 2.145, "prev_close": null, "currency": "USD", "exchange": "NCM", "market_cap": null}, "HIVE": {"ticker": "HIVE", "price": 2.45, "prev_close": null, "currency": "USD", "exchange": "NCM", "market_cap": null}, "GREE": {"ticker": "GREE", "price": 1.195, "prev_close": null, "currency": "USD", "exchange": "NMS", "market_cap": null}, "ABTC": {"ticker": "ABTC", "price": 1.205, "prev_close": null, "currency": "USD", "exchange": "NCM", "market_cap": null}, "ANY": {"ticker": "ANY", "price": 1.49, "prev_close": null, "currency": "USD", "exchange": "NCM", "market_cap": null}, "SLNH": {"ticker": "SLNH", "price": 1.601, "prev_close": null, "currency": "USD", "exchange": "NCM", "market_cap": null}, "GPUS": {"ticker": "GPUS", "price": 0.1351, "prev_close": null, "currency": "USD", "exchange": "ASE", "market_cap": null}, "DGXX": {"ticker": "DGXX", "price": 3.56, "prev_close": null, "currency": "USD", "exchange": "NCM", "market_cap": null}, "MIGI": {"ticker": "MIGI", "price": 4.71, "prev_close": null, "currency": "USD", "exchange": "NCM", "market_cap": null}, "SAIH": {"ticker": "SAIH", "price": 11.05, "prev_close": null, "currency": "USD", "exchange": "NCM", "market_cap": null}, "_BTC": {"btc_price_usd": 78245, "btc_market_cap": 1566544918930.651, "btc_24h_change_pct": 2.544076254881978}}
